prestopy/__init__.py
prestopy/prestopy.py
Prestopy-0.0.1.dist-info/LICENSE
Prestopy-0.0.1.dist-info/METADATA
Prestopy-0.0.1.dist-info/WHEEL
Prestopy-0.0.1.dist-info/top_level.txt
Prestopy-0.0.1.dist-info/RECORD
