Metadata-Version: 2.1
Name: Prestopy
Version: 0.0.1
Summary: A profiler package
Author-email: Ricardo Prins <ricardoprins@gmail.com>
License: MIT License        
Project-URL: Homepage, https://github.com/ricardoprins/prestopy
Project-URL: Bug Tracker, https://github.com/ricardoprins/prestopy/issues
Classifier: Programming Language :: Python :: 3
Classifier: License :: OSI Approved :: MIT License
Classifier: Operating System :: OS Independent
Requires-Python: >=3.9
License-File: LICENSE
